{"expireTime":9007200944091125000,"key":"transformer-remark-markdown-html-ast-a3ff50350a5db71ea657b3fcc9adf4e3-gatsby-remark-external-linksgatsby-remark-imagesgatsby-remark-code-titlesgatsby-remark-prismjs-","val":{"type":"root","children":[{"type":"element","tagName":"ul","properties":{},"children":[{"type":"text","value":"\n"},{"type":"element","tagName":"li","properties":{},"children":[{"type":"text","value":"\n"},{"type":"element","tagName":"p","properties":{},"children":[{"type":"text","value":"Express.js is the most popular backend framework for Node.js, and it is an extensive part of the JavaScript ecosystem.","position":{"start":{"line":2,"column":3,"offset":3},"end":{"line":2,"column":121,"offset":121}}}],"position":{"start":{"line":2,"column":3,"offset":3},"end":{"line":2,"column":121,"offset":121}}},{"type":"text","value":"\n"}],"position":{"start":{"line":2,"column":1,"offset":1},"end":{"line":2,"column":121,"offset":121}}},{"type":"text","value":"\n"},{"type":"element","tagName":"li","properties":{},"children":[{"type":"text","value":"\n"},{"type":"element","tagName":"p","properties":{},"children":[{"type":"text","value":"It is designed to build single-page, multi-page, and hybrid web applications, it has also become the standard for developing backend applications with Node.js, and it is the backend part of something known as the MEVN stack.","position":{"start":{"line":4,"column":3,"offset":125},"end":{"line":4,"column":227,"offset":349}}}],"position":{"start":{"line":4,"column":3,"offset":125},"end":{"line":4,"column":227,"offset":349}}},{"type":"text","value":"\n"}],"position":{"start":{"line":4,"column":1,"offset":123},"end":{"line":4,"column":227,"offset":349}}},{"type":"text","value":"\n"},{"type":"element","tagName":"li","properties":{},"children":[{"type":"text","value":"\n"},{"type":"element","tagName":"p","properties":{},"children":[{"type":"text","value":"Provided by: ","position":{"start":{"line":6,"column":3,"offset":353},"end":{"line":6,"column":16,"offset":366}}},{"type":"element","tagName":"a","properties":{"href":"https://kinsta.com/knowledgebase/what-is-express-js/","target":"_blank","rel":"nofollow noopener noreferrer"},"children":[{"type":"text","value":"https://kinsta.com/knowledgebase/what-is-express-js/","position":{"start":{"line":6,"column":16,"offset":366},"end":{"line":6,"column":68,"offset":418}}}],"position":{"start":{"line":6,"column":16,"offset":366},"end":{"line":6,"column":68,"offset":418}}}],"position":{"start":{"line":6,"column":3,"offset":353},"end":{"line":6,"column":68,"offset":418}}},{"type":"text","value":"\n"}],"position":{"start":{"line":6,"column":1,"offset":351},"end":{"line":6,"column":68,"offset":418}}},{"type":"text","value":"\n"}],"position":{"start":{"line":2,"column":1,"offset":1},"end":{"line":6,"column":68,"offset":418}}}],"position":{"start":{"line":1,"column":1,"offset":0},"end":{"line":6,"column":68,"offset":418}}}}